gopup4/__init__.py
gopup4/economic/__init__.py
gopup4/economic/cons.py
gopup4/economic/marco_cn.py
gopup4/economic/shibor.py
gopup4/event/__init__.py
gopup4/event/area_baidu.py
gopup4/event/cons.py
gopup4/event/covid.py
gopup4/event/history_daily.py
gopup4/event/hot_list.py
gopup4/fortune/__init__.py
gopup4/fortune/cons.py
gopup4/fortune/franchise.py
gopup4/fortune/itjuzi.py
gopup4/index/__init__.py
gopup4/index/baidu_decrypt.py
gopup4/index/cons.py
gopup4/index/errors.py
gopup4/index/google_request.py
gopup4/index/index_baidu.py
gopup4/index/index_google.py
gopup4/index/index_sogou.py
gopup4/index/index_toutiao.py
gopup4/index/index_weibo.py
gopup4/life/__init__.py
gopup4/life/charity.py
gopup4/life/game.py
gopup4/life/oil.py
gopup4/life/train.py
gopup4/life/university.py
gopup4/mcn/__init__.py
gopup4/mcn/cons.py
gopup4/mcn/star.py
gopup4/mcn/weibo.py
gopup4/movie/__init__.py
gopup4/movie/cons.py
gopup4/movie/movie.py
gopup4/pro/__init__.py
gopup4/pro/client.py
gopup4/pro/pro_data.py
gopup4/stock/__init__.py
gopup4/stock/classifying.py
gopup4/stock/cons.py
gopup4/stock/fund.py
gopup4/utils/__init__.py
gopup4/utils/date_utils.py
gopup4/utils/rest_agent.py
gopup4/utils/utils.py
gopup4/utils/utils_pass.py
gopup4-0.4.7.dist-info/METADATA
gopup4-0.4.7.dist-info/WHEEL
gopup4-0.4.7.dist-info/top_level.txt
gopup4-0.4.7.dist-info/RECORD
